[
    {
        "surname": "Іванов",
        "address": "вул. Шевченка, 10",
        "position": "менеджер"
    },
    {
        "surname": "Петренко",
        "address": "вул. Грушевського, 15",
        "position": "директор"
    },
    {
        "surname": "Сидоров",
        "address": "вул. Франка, 7",
        "position": "аналітик"
    },
    {
        "surname": "Коваленко",
        "address": "вул. Лесі Українки, 20",
        "position": "програміст"
    },
    {
        "surname": "Мельник",
        "address": "вул. Кобзаря, 8",
        "position": "маркетолог"
    },
    {
        "surname": "Шевченко",
        "address": "вул. Леніна, 5",
        "position": "економіст"
    },
    {
        "surname": "Коваль",
        "address": "вул. Червоноармійська, 3",
        "position": "бухгалтер"
    },
    {
        "surname": "Гречко",
        "address": "вул. Довженка, 11",
        "position": "системний адміністратор"
    },
    {
        "surname": "Кузьменко",
        "address": "вул. Пушкина, 2",
        "position": "технік"
    },
    {
        "surname": "Тимошенко",
        "address": "вул. Пирогова, 18",
        "position": "юрист"
    },
    {
        "surname": "Бабенко",
        "address": "Миру 25",
        "position": "Студент"
    }
]